essay_file_mcp_server_lc/__init__.py
essay_file_mcp_server_lc/server.py
essay_file_mcp_server_lc-0.1.2.dist-info/METADATA
essay_file_mcp_server_lc-0.1.2.dist-info/WHEEL
essay_file_mcp_server_lc-0.1.2.dist-info/entry_points.txt
essay_file_mcp_server_lc-0.1.2.dist-info/RECORD
